conflictlib/__init__.py
conflictlib/engine.py
conflictlib/rules.py
conflictlib/functions/__init__.py
conflictlib/functions/base.py
conflictlib/functions/builtins.py
tests/__init__.py
tests/benchmarking.py
tests/test_conflict_engine.py
tests/utils.py
conflictlib-0.0.7.dist-info/METADATA
conflictlib-0.0.7.dist-info/WHEEL
conflictlib-0.0.7.dist-info/top_level.txt
conflictlib-0.0.7.dist-info/RECORD
