Metadata-Version: 2.4
Name: conflictlib
Version: 0.0.7
Summary: Reusable engine for resource conflict detection
Author: Your Name
Author-email: Wade Tait <wade.tait@braingu.com>
License-Expression: MIT
Requires-Python: >=3.8
Requires-Dist: rule-engine>=4.5.0
